eflips/__init__.py
eflips/evaluation.py
eflips/helperFunctions.py
eflips/misc.py
eflips/settings.py
eflips/settings_files/default.json
eflips/settings_files/exampledata.json
eflips/simpy_ext.py
eflips-0.1.3.dist-info/METADATA
eflips-0.1.3.dist-info/WHEEL
eflips-0.1.3.dist-info/RECORD
